tasks/lesson4/task4_3/task4_3.v
module counter (
    input clk,
    input reset,
    output reg a,
    output reg b,
    output reg c,
    output reg d
);
    reg [3:0] cnt;

    assign a = cnt[0];
    assign b = cnt[1];
    assign c = cnt[2];
    assign d = cnt[3];

    always @(posedge clk or posedge reset) begin
        if (reset)
            cnt <= 0;
        else
            cnt <= cnt + 1;
    end
endmodule

tasks/lesson4/task4_3/test4_3.v
`timescale 1ns/1ps

module tb;

    reg clk = 0;
    reg reset = 0;
    reg led1;
    reg led2;
    reg led3;
    reg led4;

    counter cnt(clk, reset, led1, led2, led3, led4);

    initial begin
        $dumpfile("dump.vcd");
        $dumpvars(0, tb);

        #10;
        reset = 1;
        #10;
        reset = 0;
        #5
        clk = !clk;
        #5
        clk = !clk;
        #5
        clk = !clk;
        #5
        clk = !clk;
        #5
        clk = !clk;
        #5
        clk = !clk;
        #5
        clk = !clk;
        #5
        clk = !clk;
        #5
        clk = !clk;
        #5
        clk = !clk;
        #5
        clk = !clk;
        #5
        clk = !clk;
        #5
        clk = !clk;
        #5
        clk = !clk;
        #5
        clk = !clk;
        #5
        clk = !clk;
        #5
        clk = !clk;
        #5
        clk = !clk;
        #5
        clk = !clk;
        #5
        clk = !clk;
        #5
        clk = !clk;
        #5
        clk = !clk;
        #5
        clk = !clk;
        #5
        clk = !clk;
        #5
        clk = !clk;
        #5
        clk = !clk;
        #5
        clk = !clk;
        #5
        clk = !clk;
        #5
        clk = !clk;
        #5
        clk = !clk;
        #5
        clk = !clk;
        #5
        clk = !clk;
        #5
        clk = !clk;
        #5
        clk = !clk;
        #5
        clk = !clk;
        #5
        clk = !clk;
        #5
        clk = !clk;
        #5
        $finish;
    end

endmodule

tasks/lesson4/task4_3/dump.vcd
$version Generated by VerilatedVcd $end
$timescale 1ps $end
 $scope module tb $end
  $var wire 1 ' clk $end
  $var wire 1 ( reset $end
  $var wire 1 " led1 $end
  $var wire 1 # led2 $end
  $var wire 1 $ led3 $end
  $var wire 1 % led4 $end
  $scope module cnt $end
   $var wire 1 ' clk $end
   $var wire 1 ( reset $end
   $var wire 1 " a $end
   $var wire 1 # b $end
   $var wire 1 $ c $end
   $var wire 1 % d $end
   $var wire 4 & cnt [3:0] $end
  $upscope $end
 $upscope $end
$enddefinitions $end


#0
0"
0#
0$
0%
b0000 &
0'
0(
#10000
1(
#20000
0(
#25000
1"
b0001 &
1'
#30000
0'
#35000
0"
1#
b0010 &
1'
#40000
0'
#45000
1"
b0011 &
1'
#50000
0'
#55000
0"
0#
1$
b0100 &
1'
#60000
0'
#65000
1"
b0101 &
1'
#70000
0'
#75000
0"
1#
b0110 &
1'
#80000
0'
#85000
1"
b0111 &
1'
#90000
0'
#95000
0"
0#
0$
1%
b1000 &
1'
#100000
0'
#105000
1"
b1001 &
1'
#110000
0'
#115000
0"
1#
b1010 &
1'
#120000
0'
#125000
1"
b1011 &
1'
#130000
0'
#135000
0"
0#
1$
b1100 &
1'
#140000
0'
#145000
1"
b1101 &
1'
#150000
0'
#155000
0"
1#
b1110 &
1'
#160000
0'
#165000
1"
b1111 &
1'
#170000
0'
#175000
0"
0#
0$
0%
b0000 &
1'
#180000
0'
#185000
1"
b0001 &
1'
#190000
0'
#195000
0"
1#
b0010 &
1'
#200000
0'
#205000
1"
b0011 &
1'
